agentc_core/__init__.py
agentc_core/activity/__init__.py
agentc_core/activity/logger/__init__.py
agentc_core/activity/logger/base.py
agentc_core/activity/logger/chain.py
agentc_core/activity/logger/db.py
agentc_core/activity/logger/local.py
agentc_core/activity/models/__init__.py
agentc_core/activity/models/content.py
agentc_core/activity/models/log.py
agentc_core/activity/remote/__init__.py
agentc_core/activity/remote/analytics/1.sessions.sqlpp
agentc_core/activity/remote/analytics/2.last_session.sqlpp
agentc_core/activity/remote/analytics/3.exchanges.sqlpp
agentc_core/activity/remote/analytics/4.tool_invocations.sqlpp
agentc_core/activity/remote/create.py
agentc_core/activity/remote/query/1.sessions.sqlpp
agentc_core/activity/remote/query/2.last_session.sqlpp
agentc_core/activity/remote/query/3.exchanges.sqlpp
agentc_core/activity/remote/query/4.tool_invocations.sqlpp
agentc_core/activity/span.py
agentc_core/annotation/__init__.py
agentc_core/annotation/annotation.py
agentc_core/catalog/__init__.py
agentc_core/catalog/catalog.py
agentc_core/catalog/descriptor.py
agentc_core/catalog/directory.py
agentc_core/catalog/implementations/__init__.py
agentc_core/catalog/implementations/base.py
agentc_core/catalog/implementations/chain.py
agentc_core/catalog/implementations/db.py
agentc_core/catalog/implementations/mem.py
agentc_core/catalog/index.py
agentc_core/catalog/version.py
agentc_core/config/__init__.py
agentc_core/config/config.py
agentc_core/defaults.py
agentc_core/evaluation/__init__.py
agentc_core/evaluation/decorator.py
agentc_core/evaluation/evaluate.py
agentc_core/indexer/__init__.py
agentc_core/indexer/indexer.py
agentc_core/learned/__init__.py
agentc_core/learned/embedding.py
agentc_core/learned/model.py
agentc_core/prompt/__init__.py
agentc_core/prompt/models.py
agentc_core/prompt/templates/prompt.jinja
agentc_core/provider/__init__.py
agentc_core/provider/loader.py
agentc_core/provider/provider.py
agentc_core/provider/refiner.py
agentc_core-0.2.1a1.dist-info/METADATA
agentc_core-0.2.1a1.dist-info/WHEEL
agentc_core-0.2.1a1.dist-info/RECORD
